singlestoredb/__init__.py
singlestoredb/auth.py
singlestoredb/config.py
singlestoredb/connection.py
singlestoredb/converters.py
singlestoredb/exceptions.py
singlestoredb/py.typed
singlestoredb/pytest.py
singlestoredb/types.py
singlestoredb/vectorstore.py
singlestoredb/warnings.py
singlestoredb/ai/__init__.py
singlestoredb/ai/chat.py
singlestoredb/ai/embeddings.py
singlestoredb/alchemy/__init__.py
singlestoredb/apps/__init__.py
singlestoredb/apps/_cloud_functions.py
singlestoredb/apps/_config.py
singlestoredb/apps/_connection_info.py
singlestoredb/apps/_dashboards.py
singlestoredb/apps/_process.py
singlestoredb/apps/_python_udfs.py
singlestoredb/apps/_stdout_supress.py
singlestoredb/apps/_uvicorn_util.py
singlestoredb/docstring/__init__.py
singlestoredb/docstring/attrdoc.py
singlestoredb/docstring/common.py
singlestoredb/docstring/epydoc.py
singlestoredb/docstring/google.py
singlestoredb/docstring/numpydoc.py
singlestoredb/docstring/parser.py
singlestoredb/docstring/py.typed
singlestoredb/docstring/rest.py
singlestoredb/docstring/util.py
singlestoredb/docstring/tests/__init__.py
singlestoredb/docstring/tests/_pydoctor.py
singlestoredb/docstring/tests/test_epydoc.py
singlestoredb/docstring/tests/test_google.py
singlestoredb/docstring/tests/test_numpydoc.py
singlestoredb/docstring/tests/test_parse_from_object.py
singlestoredb/docstring/tests/test_parser.py
singlestoredb/docstring/tests/test_rest.py
singlestoredb/docstring/tests/test_util.py
singlestoredb/functions/__init__.py
singlestoredb/functions/decorator.py
singlestoredb/functions/dtypes.py
singlestoredb/functions/signature.py
singlestoredb/functions/utils.py
singlestoredb/functions/ext/__init__.py
singlestoredb/functions/ext/arrow.py
singlestoredb/functions/ext/asgi.py
singlestoredb/functions/ext/json.py
singlestoredb/functions/ext/mmap.py
singlestoredb/functions/ext/rowdat_1.py
singlestoredb/functions/ext/timer.py
singlestoredb/functions/ext/utils.py
singlestoredb/functions/typing/__init__.py
singlestoredb-1.16.8.dist-info/licenses/LICENSE
singlestoredb-1.16.8.dist-info/METADATA
singlestoredb-1.16.8.dist-info/WHEEL
singlestoredb-1.16.8.dist-info/entry_points.txt
singlestoredb-1.16.8.dist-info/top_level.txt
singlestoredb-1.16.8.dist-info/RECORD
